MANIFEST.in
README.txt
setup.py
c2/__init__.py
c2.patch.z3cformdateinput.egg-info/PKG-INFO
c2.patch.z3cformdateinput.egg-info/SOURCES.txt
c2.patch.z3cformdateinput.egg-info/dependency_links.txt
c2.patch.z3cformdateinput.egg-info/entry_points.txt
c2.patch.z3cformdateinput.egg-info/namespace_packages.txt
c2.patch.z3cformdateinput.egg-info/not-zip-safe
c2.patch.z3cformdateinput.egg-info/requires.txt
c2.patch.z3cformdateinput.egg-info/top_level.txt
c2/patch/__init__.py
c2/patch/z3cformdateinput/__init__.py
c2/patch/z3cformdateinput/configure.zcml
c2/patch/z3cformdateinput/overrides.zcml
c2/patch/z3cformdateinput/tests.py
c2/patch/z3cformdateinput/version.txt
c2/patch/z3cformdateinput/templates/date_display.pt
c2/patch/z3cformdateinput/templates/date_input.pt
c2/patch/z3cformdateinput/templates/datetime_display.pt
c2/patch/z3cformdateinput/templates/datetime_input.pt
docs/HISTORY.txt
docs/INSTALL.txt
docs/LICENSE.GPL
docs/LICENSE.txt