Metadata-Version: 1.0
Name: c2.patch.z3cformdateinput
Version: 1.0a1
Summary: This product is monkey patch for z3cform date input box for Japanese style
Home-page: http://wwww.cmscom.jp
Author: Manabu TERADA
Author-email: terada@cmscom.jp
License: GPL
Keywords: plone patch dateinput dexterity
Platform: UNKNOWN
Classifier: Framework :: Plone
Classifier: Programming Language :: Python
